AA23028UNO/__init__.py
AA23028UNO/solvers.py
AA23028UNO-0.1.0.dist-info/METADATA
AA23028UNO-0.1.0.dist-info/WHEEL
AA23028UNO-0.1.0.dist-info/top_level.txt
AA23028UNO-0.1.0.dist-info/RECORD
