Metadata-Version: 2.1
Name: AA23028UNO
Version: 0.1.0
Summary: Librería de métodos numéricos para sistemas de ecuaciones lineales y no lineales
Home-page: https://pypi.org/project/AA23028UNO/
Author: Alexis Aldana
License: MIT
Requires-Python: >=3.7
Requires-Dist: numpy
Requires-Dist: scipy
